SuPyMode/VERSION
SuPyMode/__debug__.py
SuPyMode/__init__.py
SuPyMode/profiles.py
SuPyMode/representations.py
SuPyMode/slice_structure.py
SuPyMode/solver.py
SuPyMode/supermode.py
SuPyMode/superset.py
SuPyMode/symmetries.py
SuPyMode/workflow.py
SuPyMode/binary/CppSolver.cp310-win_amd64.pyd
SuPyMode/binary/SuperMode.cp310-win_amd64.pyd
SuPyMode/binary/__init__.py
SuPyMode/cpp/eigensolver_interface.cpp
SuPyMode/cpp/supermode_interface.cpp
SuPyMode/cpp/includes/definitions.cpp
SuPyMode/cpp/includes/eigen_solver.cpp
SuPyMode/cpp/includes/eigensolver.cpp
SuPyMode/cpp/includes/equations.cpp
SuPyMode/cpp/includes/extrapolate.cpp
SuPyMode/cpp/includes/laplacian.cpp
SuPyMode/cpp/includes/numpy_interface.cpp
SuPyMode/cpp/includes/power_shift_iteration.cpp
SuPyMode/cpp/includes/progressbar.cpp
SuPyMode/cpp/includes/ritz_iteration.cpp
SuPyMode/cpp/includes/supermode.cpp
SuPyMode/cpp/includes/supermode.h
SuPyMode/cpp/includes/utils.cpp
SuPyMode/python_debuging/__init__.py
SuPyMode/python_debuging/eigen_solver.py
SuPyMode/python_debuging/mode_solver.py
SuPyMode/tools/__init__.py
SuPyMode/tools/directories.py
SuPyMode/tools/mode_label.py
SuPyMode/tools/plot_style.py
SuPyMode/tools/special.py
SuPyMode/tools/utils.py
SuPyMode/validation_data/SBB_figure_4_16_a/LP01-LP02.csv
SuPyMode/validation_data/SBB_figure_4_16_a/LP01-LP21.csv
SuPyMode/validation_data/SBB_figure_4_16_a/LP01-LP41.csv
SuPyMode/validation_data/SBB_figure_4_16_a/LP11-LP12.csv
SuPyMode/validation_data/SBB_figure_4_16_a/LP11-LP31.csv
SuPyMode/validation_data/SBB_figure_4_16_a/LP11-LP51.csv
SuPyMode/validation_data/SBB_figure_4_16_b/LP01-LP02.csv
SuPyMode/validation_data/SBB_figure_4_16_b/LP01-LP21.csv
SuPyMode/validation_data/SBB_figure_4_16_b/LP01-LP41.csv
SuPyMode/validation_data/SBB_figure_4_16_b/LP11-LP12.csv
SuPyMode/validation_data/SBB_figure_4_16_b/LP11-LP31.csv
SuPyMode/validation_data/SBB_figure_4_16_b/LP11-LP51.csv
SuPyMode-5.1.6.dist-info/LICENSE
SuPyMode-5.1.6.dist-info/METADATA
SuPyMode-5.1.6.dist-info/WHEEL
SuPyMode-5.1.6.dist-info/top_level.txt
SuPyMode-5.1.6.dist-info/RECORD
