Metadata-Version: 2.1
Name: SuPyMode
Version: 5.1.6
Summary: A package for light propagation in fiber optics.
Home-page: https://github.com/MartinPdeS/SuPyMode
Author: Martin Poinsinet de Sivry
Author-email: Martin.poinsinet.de.sivry@gmail.com
License: MIT
Platform: unix
Platform: linux
Platform: osx
Platform: windows
Classifier: Programming Language :: Python
Classifier: Programming Language :: Python :: 3
Classifier: Programming Language :: Python :: 3.10
Classifier: Programming Language :: Python :: 3.11
Classifier: Programming Language :: Python :: Implementation :: CPython
Classifier: Development Status :: 4 - Beta
Classifier: Operating System :: OS Independent
Classifier: Topic :: Scientific/Engineering :: Physics
Classifier: Intended Audience :: Telecommunications Industry
Classifier: Intended Audience :: Science/Research
License-File: LICENSE
Requires-Dist: MPSPlots
Requires-Dist: PyFinitDiff
Requires-Dist: FiberFusing
Requires-Dist: numpy
Requires-Dist: scipy
Requires-Dist: matplotlib
Requires-Dist: pathvalidate
Provides-Extra: development
Requires-Dist: numpydoc ==1.5.0 ; extra == 'development'
Requires-Dist: sphinx >5.1.1 ; extra == 'development'
Requires-Dist: sphinx-gallery ==0.11.1 ; extra == 'development'
Requires-Dist: sphinx-rtd-theme ==1.0.0 ; extra == 'development'
Requires-Dist: numpydoc ; extra == 'development'
Requires-Dist: pydata-sphinx-theme ; extra == 'development'
Requires-Dist: pytest >=0.6 ; extra == 'development'
Requires-Dist: pytest-cov >=2.0 ; extra == 'development'
Requires-Dist: pytest-json-report ; extra == 'development'
Requires-Dist: mypy >=0.910 ; extra == 'development'
Requires-Dist: flake8 >=3.9 ; extra == 'development'
Requires-Dist: tox >=3.24 ; extra == 'development'
Requires-Dist: coverage ; extra == 'development'
Requires-Dist: PyFiberModes ; extra == 'development'
Provides-Extra: documentation
Requires-Dist: numpydoc ==1.5.0 ; extra == 'documentation'
Requires-Dist: sphinx >5.1.1 ; extra == 'documentation'
Requires-Dist: sphinx-gallery ==0.11.1 ; extra == 'documentation'
Requires-Dist: sphinx-rtd-theme ==1.0.0 ; extra == 'documentation'
Requires-Dist: numpydoc ; extra == 'documentation'
Requires-Dist: pydata-sphinx-theme ; extra == 'documentation'
Provides-Extra: testing
Requires-Dist: pytest >=0.6 ; extra == 'testing'
Requires-Dist: pytest-cov >=2.0 ; extra == 'testing'
Requires-Dist: pytest-json-report ; extra == 'testing'
Requires-Dist: mypy >=0.910 ; extra == 'testing'
Requires-Dist: flake8 >=3.9 ; extra == 'testing'
Requires-Dist: tox >=3.24 ; extra == 'testing'
Requires-Dist: coverage ; extra == 'testing'
Requires-Dist: PyFiberModes ; extra == 'testing'
